bourstadlib/__init__.py
bourstadlib/_internal/__init__.py
bourstadlib/_internal/_apis/__init__.py
bourstadlib/_internal/_apis/fmp.py
bourstadlib/_internal/_config.py
bourstadlib/_internal/_exceptions.py
bourstadlib/config.py
bourstadlib-0.0.2.dist-info/METADATA
bourstadlib-0.0.2.dist-info/WHEEL
bourstadlib-0.0.2.dist-info/RECORD
