Metadata-Version: 2.1
Name: bourstadlib
Version: 0.0.2
Summary: 
License: MIT
Author: Charles Dupont
Author-email: charlo.dupont@gmail.com
Requires-Python: >=3.12.1,<4.0.0
Classifier: License :: OSI Approved :: MIT License
Classifier: Programming Language :: Python :: 3
Provides-Extra: mysql
Provides-Extra: postgresql
Requires-Dist: pandas (>=2.2.0,<3.0.0)
Requires-Dist: psycopg2 (>=2.9.9,<3.0.0) ; extra == "postgresql"
Requires-Dist: pymysql (>=1.1.0,<2.0.0) ; extra == "mysql"
Requires-Dist: python-decouple (>=3.8,<4.0)
Requires-Dist: requests (>=2.31.0,<3.0.0)
Requires-Dist: sqlalchemy (>=2.0.27,<3.0.0)
